pyc3/__init__.py
pyc3/c3.py
pyc3/data/most_salient_colors.txt
pyc3/data/xkcd/c3_data.json
pyc3/data/xkcd/cosine_distances_square.npy
pyc3/pyc3.py
pyc3-0.3.10.dist-info/WHEEL
pyc3-0.3.10.dist-info/METADATA
pyc3-0.3.10.dist-info/RECORD
