Metadata-Version: 2.1
Name: pyc3
Version: 0.3.10
Summary: 
Home-page: https://github.com/simonwarchol/pyc3
Author: Simon Warchol
Author-email: simonwarchol@g.harvard.edu
Requires-Python: >=3.8,<4.0
Classifier: Programming Language :: Python :: 3
Classifier: Programming Language :: Python :: 3.10
Classifier: Programming Language :: Python :: 3.8
Classifier: Programming Language :: Python :: 3.9
Requires-Dist: colorutil (==0.9.9)
Requires-Dist: numpy (>=1.21.6,<2.0.0)
Requires-Dist: scikit-learn (>=1.2.1,<2.0.0)
Requires-Dist: scipy (==1.9.3)
Requires-Dist: tqdm (>=4.64.1,<5.0.0)
Project-URL: Repository, https://github.com/simonwarchol/pyc3
